MANIFEST.in
README
REQUIREMENTS
distribute_setup.py
setup.py
src/django_ctrl.egg-info/PKG-INFO
src/django_ctrl.egg-info/SOURCES.txt
src/django_ctrl.egg-info/dependency_links.txt
src/django_ctrl.egg-info/requires.txt
src/django_ctrl.egg-info/top_level.txt
src/djctrl/__init__.py
src/djctrl/core.py
src/djctrl/common/__init__.py
src/djctrl/common/ajax.py
src/djctrl/common/auth.py
src/djctrl/common/cache.py
src/djctrl/common/form.py
src/djctrl/common/mime.py
src/djctrl/common/resource.py