Metadata-Version: 1.0
Name: django-ctrl
Version: 2.1
Summary: An implementation of Controllers for Django.
Home-page: http://bitbucket.org/zacharyvoase/django-ctrl
Author: Zachary Voase
Author-email: zacharyvoase@me.com
License: UNKNOWN
Platform: UNKNOWN
